train_route/__init__.py
train_route/path.py
train_route/schedule.py
train_route/segment.py
train_route/train.py
train_route/train_render.py
train_route/train_system.py
train_route/utils.py
train_route-1.0.0.dist-info/LICENSE
train_route-1.0.0.dist-info/METADATA
train_route-1.0.0.dist-info/WHEEL
train_route-1.0.0.dist-info/RECORD
