Metadata-Version: 2.1
Name: train-route
Version: 1.0.0
Summary: 
Author: Samarin Aleksei
Author-email: liotbiu1@gmail.com
Requires-Python: >=3.9,<4.0
Classifier: Programming Language :: Python :: 3
Classifier: Programming Language :: Python :: 3.9
Classifier: Programming Language :: Python :: 3.10
Classifier: Programming Language :: Python :: 3.11
Classifier: Programming Language :: Python :: 3.12
Requires-Dist: pyproj (>=3.6.1,<4.0.0)
